{
  "": [
    {
      "country": "Diamond Princess",
      "continent": "",
      "totalCases": 712.0,
      "totalDeaths": 13.0,
      "totalRecovered": 651.0,
      "activeCases": 48.0,
      "critical": 4.0
    }
  ],
  "South America": [
    {
      "country": "Brazil",
      "continent": "South America",
      "population": 2.12710692E8,
      "totalCases": 2917562.0,
      "totalDeaths": 98644.0,
      "totalRecovered": 2047660.0,
      "activeCases": 771258.0,
      "critical": 8318.0,
      "totalCases1M": 13716.0,
      "deaths1M": 464.0,
      "totalTests": 1.3206188E7,
      "tests1M": 62085.0
    },
    {
      "country": "Peru",
      "continent": "South America",
      "population": 3.3016319E7,
      "totalCases": 455409.0,
      "totalDeaths": 20424.0,
      "totalRecovered": 310337.0,
      "activeCases": 124648.0,
      "critical": 1426.0,
      "totalCases1M": 13793.0,
      "deaths1M": 619.0,
      "totalTests": 2493429.0,
      "tests1M": 75521.0
    },
    {
      "country": "Chile",
      "continent": "South America",
      "population": 1.9132514E7,
      "totalCases": 366671.0,
      "totalDeaths": 9889.0,
      "totalRecovered": 340168.0,
      "activeCases": 16614.0,
      "critical": 1358.0,
      "totalCases1M": 19165.0,
      "deaths1M": 517.0,
      "totalTests": 1760615.0,
      "tests1M": 92022.0
    },
    {
      "country": "Colombia",
      "continent": "South America",
      "population": 5.0936262E7,
      "totalCases": 357710.0,
      "totalDeaths": 11939.0,
      "totalRecovered": 192355.0,
      "activeCases": 153416.0,
      "critical": 1493.0,
      "totalCases1M": 7023.0,
      "deaths1M": 234.0,
      "totalTests": 1801835.0,
      "tests1M": 35374.0
    },
    {
      "country": "Argentina",
      "continent": "South America",
      "population": 4.5236884E7,
      "totalCases": 228195.0,
      "totalDeaths": 4251.0,
      "totalRecovered": 99852.0,
      "activeCases": 124092.0,
      "critical": 1150.0,
      "totalCases1M": 5044.0,
      "deaths1M": 94.0,
      "totalTests": 794544.0,
      "tests1M": 17564.0
    },
    {
      "country": "Ecuador",
      "continent": "South America",
      "population": 1.7668824E7,
      "totalCases": 90537.0,
      "totalDeaths": 5877.0,
      "totalRecovered": 71318.0,
      "activeCases": 13342.0,
      "critical": 378.0,
      "totalCases1M": 5124.0,
      "deaths1M": 333.0,
      "totalTests": 258582.0,
      "tests1M": 14635.0
    },
    {
      "country": "Bolivia",
      "continent": "South America",
      "population": 1.1688459E7,
      "totalCases": 86423.0,
      "totalDeaths": 3465.0,
      "totalRecovered": 27373.0,
      "activeCases": 55585.0,
      "critical": 71.0,
      "totalCases1M": 7394.0,
      "deaths1M": 296.0,
      "totalTests": 183583.0,
      "tests1M": 15706.0
    },
    {
      "country": "Venezuela",
      "continent": "South America",
      "population": 2.8427499E7,
      "totalCases": 22299.0,
      "totalDeaths": 195.0,
      "totalRecovered": 12146.0,
      "activeCases": 9958.0,
      "critical": 42.0,
      "totalCases1M": 784.0,
      "deaths1M": 7.0,
      "totalTests": 1567431.0,
      "tests1M": 55138.0
    },
    {
      "country": "French Guiana",
      "continent": "South America",
      "population": 299385.0,
      "totalCases": 8127.0,
      "totalDeaths": 47.0,
      "totalRecovered": 7240.0,
      "activeCases": 840.0,
      "critical": 23.0,
      "totalCases1M": 27146.0,
      "deaths1M": 157.0,
      "totalTests": 41412.0,
      "tests1M": 138324.0
    },
    {
      "country": "Paraguay",
      "continent": "South America",
      "population": 7141091.0,
      "totalCases": 6375.0,
      "totalDeaths": 66.0,
      "totalRecovered": 4974.0,
      "activeCases": 1335.0,
      "critical": 23.0,
      "totalCases1M": 893.0,
      "deaths1M": 9.0,
      "totalTests": 135277.0,
      "tests1M": 18943.0
    },
    {
      "country": "Suriname",
      "continent": "South America",
      "population": 587154.0,
      "totalCases": 2096.0,
      "totalDeaths": 29.0,
      "totalRecovered": 1446.0,
      "activeCases": 621.0,
      "critical": 9.0,
      "totalCases1M": 3570.0,
      "deaths1M": 49.0,
      "totalTests": 2785.0,
      "tests1M": 4743.0
    },
    {
      "country": "Uruguay",
      "continent": "South America",
      "population": 3474956.0,
      "totalCases": 1318.0,
      "totalDeaths": 37.0,
      "totalRecovered": 1079.0,
      "activeCases": 202.0,
      "critical": 2.0,
      "totalCases1M": 379.0,
      "deaths1M": 11.0,
      "totalTests": 126956.0,
      "tests1M": 36535.0
    },
    {
      "country": "Guyana",
      "continent": "South America",
      "population": 786936.0,
      "totalCases": 538.0,
      "totalDeaths": 22.0,
      "totalRecovered": 189.0,
      "activeCases": 327.0,
      "critical": 2.0,
      "totalCases1M": 684.0,
      "deaths1M": 28.0,
      "totalTests": 5165.0,
      "tests1M": 6563.0
    },
    {
      "country": "Falkland Islands",
      "continent": "South America",
      "population": 3489.0,
      "totalCases": 13.0,
      "totalRecovered": 13.0,
      "activeCases": 0.0,
      "totalCases1M": 3726.0,
      "totalTests": 1816.0,
      "tests1M": 520493.0
    }
  ],
  "Asia": [
    {
      "country": "India",
      "continent": "Asia",
      "population": 1.381344997E9,
      "totalCases": 2025409.0,
      "totalDeaths": 41638.0,
      "totalRecovered": 1377384.0,
      "activeCases": 606387.0,
      "critical": 8944.0,
      "totalCases1M": 1466.0,
      "deaths1M": 30.0,
      "totalTests": 2.2149351E7,
      "tests1M": 16035.0
    },
    {
      "country": "Iran",
      "continent": "Asia",
      "population": 8.4097623E7,
      "totalCases": 320117.0,
      "totalDeaths": 17976.0,
      "totalRecovered": 277463.0,
      "activeCases": 24678.0,
      "critical": 4156.0,
      "totalCases1M": 3806.0,
      "deaths1M": 214.0,
      "totalTests": 2612763.0,
      "tests1M": 31068.0
    },
    {
      "country": "Saudi Arabia",
      "continent": "Asia",
      "population": 3.4865919E7,
      "totalCases": 284226.0,
      "totalDeaths": 3055.0,
      "totalRecovered": 247089.0,
      "activeCases": 34082.0,
      "critical": 1915.0,
      "totalCases1M": 8152.0,
      "deaths1M": 88.0,
      "totalTests": 3635705.0,
      "tests1M": 104277.0
    },
    {
      "country": "Pakistan",
      "continent": "Asia",
      "population": 2.21295851E8,
      "totalCases": 281863.0,
      "totalDeaths": 6035.0,
      "totalRecovered": 256058.0,
      "activeCases": 19770.0,
      "critical": 809.0,
      "totalCases1M": 1274.0,
      "deaths1M": 27.0,
      "totalTests": 2058872.0,
      "tests1M": 9304.0
    },
    {
      "country": "Bangladesh",
      "continent": "Asia",
      "population": 1.64851401E8,
      "totalCases": 249651.0,
      "totalDeaths": 3306.0,
      "totalRecovered": 143824.0,
      "activeCases": 102521.0,
      "totalCases1M": 1514.0,
      "deaths1M": 20.0,
      "totalTests": 1225124.0,
      "tests1M": 7432.0
    },
    {
      "country": "Turkey",
      "continent": "Asia",
      "population": 8.4428331E7,
      "totalCases": 237265.0,
      "totalDeaths": 5798.0,
      "totalRecovered": 220546.0,
      "activeCases": 10921.0,
      "critical": 580.0,
      "totalCases1M": 2810.0,
      "deaths1M": 69.0,
      "totalTests": 5081802.0,
      "tests1M": 60191.0
    },
    {
      "country": "Iraq",
      "continent": "Asia",
      "population": 4.0306025E7,
      "totalCases": 140603.0,
      "totalDeaths": 5161.0,
      "totalRecovered": 101025.0,
      "activeCases": 34417.0,
      "critical": 517.0,
      "totalCases1M": 3488.0,
      "deaths1M": 128.0,
      "totalTests": 1092741.0,
      "tests1M": 27111.0
    },
    {
      "country": "Philippines",
      "continent": "Asia",
      "population": 1.09722719E8,
      "totalCases": 119460.0,
      "totalDeaths": 2150.0,
      "totalRecovered": 66837.0,
      "activeCases": 50473.0,
      "critical": 239.0,
      "totalCases1M": 1089.0,
      "deaths1M": 20.0,
      "totalTests": 1669996.0,
      "tests1M": 15220.0
    },
    {
      "country": "Indonesia",
      "continent": "Asia",
      "population": 2.73808365E8,
      "totalCases": 118753.0,
      "totalDeaths": 5521.0,
      "totalRecovered": 75645.0,
      "activeCases": 37587.0,
      "totalCases1M": 434.0,
      "deaths1M": 20.0,
      "totalTests": 1633156.0,
      "tests1M": 5965.0
    },
    {
      "country": "Qatar",
      "continent": "Asia",
      "population": 2807805.0,
      "totalCases": 112092.0,
      "totalDeaths": 178.0,
      "totalRecovered": 108831.0,
      "activeCases": 3083.0,
      "critical": 77.0,
      "totalCases1M": 39922.0,
      "deaths1M": 63.0,
      "totalTests": 511000.0,
      "tests1M": 181993.0
    },
    {
      "country": "Kazakhstan",
      "continent": "Asia",
      "population": 1.8798667E7,
      "totalCases": 95942.0,
      "totalDeaths": 1058.0,
      "totalRecovered": 68871.0,
      "activeCases": 26013.0,
      "critical": 221.0,
      "totalCases1M": 5104.0,
      "deaths1M": 56.0,
      "totalTests": 2163713.0,
      "tests1M": 115099.0
    },
    {
      "country": "Oman",
      "continent": "Asia",
      "population": 5118446.0,
      "totalCases": 80713.0,
      "totalDeaths": 492.0,
      "totalRecovered": 70910.0,
      "activeCases": 9311.0,
      "critical": 177.0,
      "totalCases1M": 15769.0,
      "deaths1M": 96.0,
      "totalTests": 309212.0,
      "tests1M": 60411.0
    },
    {
      "country": "Israel",
      "continent": "Asia",
      "population": 9197590.0,
      "totalCases": 79559.0,
      "totalDeaths": 576.0,
      "totalRecovered": 53427.0,
      "activeCases": 25556.0,
      "critical": 358.0,
      "totalCases1M": 8650.0,
      "deaths1M": 63.0,
      "totalTests": 1872453.0,
      "tests1M": 203581.0
    },
    {
      "country": "Kuwait",
      "continent": "Asia",
      "population": 4276658.0,
      "totalCases": 70045.0,
      "totalDeaths": 469.0,
      "totalRecovered": 61610.0,
      "activeCases": 7966.0,
      "critical": 127.0,
      "totalCases1M": 16378.0,
      "deaths1M": 110.0,
      "totalTests": 522200.0,
      "tests1M": 122105.0
    },
    {
      "country": "UAE",
      "continent": "Asia",
      "population": 9902079.0,
      "totalCases": 61845.0,
      "totalDeaths": 354.0,
      "totalRecovered": 55739.0,
      "activeCases": 5752.0,
      "totalCases1M": 6246.0,
      "deaths1M": 36.0,
      "totalTests": 5262658.0,
      "tests1M": 531470.0
    },
    {
      "country": "Singapore",
      "continent": "Asia",
      "population": 5854932.0,
      "totalCases": 54555.0,
      "totalDeaths": 27.0,
      "totalRecovered": 48031.0,
      "activeCases": 6497.0,
      "totalCases1M": 9318.0,
      "deaths1M": 5.0,
      "totalTests": 1474372.0,
      "tests1M": 251817.0
    },
    {
      "country": "Bahrain",
      "continent": "Asia",
      "population": 1706669.0,
      "totalCases": 42889.0,
      "totalDeaths": 156.0,
      "totalRecovered": 39945.0,
      "activeCases": 2788.0,
      "critical": 41.0,
      "totalCases1M": 25130.0,
      "deaths1M": 91.0,
      "totalTests": 876700.0,
      "tests1M": 513691.0
    },
    {
      "country": "Japan",
      "continent": "Asia",
      "population": 1.26435859E8,
      "totalCases": 42263.0,
      "totalDeaths": 1026.0,
      "totalRecovered": 28877.0,
      "activeCases": 12360.0,
      "critical": 115.0,
      "totalCases1M": 334.0,
      "deaths1M": 8.0,
      "totalTests": 938739.0,
      "tests1M": 7425.0
    },
    {
      "country": "Armenia",
      "continent": "Asia",
      "population": 2963811.0,
      "totalCases": 39819.0,
      "totalDeaths": 772.0,
      "totalRecovered": 31556.0,
      "activeCases": 7491.0,
      "totalCases1M": 13435.0,
      "deaths1M": 260.0,
      "totalTests": 171600.0,
      "tests1M": 57898.0
    },
    {
      "country": "Kyrgyzstan",
      "continent": "Asia",
      "population": 6534479.0,
      "totalCases": 38659.0,
      "totalDeaths": 1447.0,
      "totalRecovered": 30099.0,
      "activeCases": 7113.0,
      "critical": 24.0,
      "totalCases1M": 5916.0,
      "deaths1M": 221.0,
      "totalTests": 267718.0,
      "tests1M": 40970.0
    },
    {
      "country": "Afghanistan",
      "continent": "Asia",
      "population": 3.9009447E7,
      "totalCases": 36896.0,
      "totalDeaths": 1298.0,
      "totalRecovered": 25840.0,
      "activeCases": 9758.0,
      "critical": 31.0,
      "totalCases1M": 946.0,
      "deaths1M": 33.0,
      "totalTests": 90396.0,
      "tests1M": 2317.0
    },
    {
      "country": "Azerbaijan",
      "continent": "Asia",
      "population": 1.0148243E7,
      "totalCases": 33247.0,
      "totalDeaths": 479.0,
      "totalRecovered": 29275.0,
      "activeCases": 3493.0,
      "critical": 66.0,
      "totalCases1M": 3276.0,
      "deaths1M": 47.0,
      "totalTests": 766179.0,
      "tests1M": 75499.0
    },
    {
      "country": "Uzbekistan",
      "continent": "Asia",
      "population": 3.3516027E7,
      "totalCases": 28315.0,
      "totalDeaths": 175.0,
      "totalRecovered": 19291.0,
      "activeCases": 8849.0,
      "critical": 228.0,
      "totalCases1M": 845.0,
      "deaths1M": 5.0,
      "totalTests": 1377915.0,
      "tests1M": 41112.0
    },
    {
      "country": "Nepal",
      "continent": "Asia",
      "population": 2.9186486E7,
      "totalCases": 21750.0,
      "totalDeaths": 65.0,
      "totalRecovered": 15389.0,
      "activeCases": 6296.0,
      "totalCases1M": 745.0,
      "deaths1M": 2.0,
      "totalTests": 731977.0,
      "tests1M": 25079.0
    },
    {
      "country": "S. Korea",
      "continent": "Asia",
      "population": 5.1273732E7,
      "totalCases": 14519.0,
      "totalDeaths": 303.0,
      "totalRecovered": 13543.0,
      "activeCases": 673.0,
      "critical": 18.0,
      "totalCases1M": 283.0,
      "deaths1M": 6.0,
      "totalTests": 1613652.0,
      "tests1M": 31471.0
    },
    {
      "country": "Palestine",
      "continent": "Asia",
      "population": 5112340.0,
      "totalCases": 13398.0,
      "totalDeaths": 92.0,
      "totalRecovered": 6907.0,
      "activeCases": 6399.0,
      "totalCases1M": 2621.0,
      "deaths1M": 18.0,
      "totalTests": 200280.0,
      "tests1M": 39176.0
    },
    {
      "country": "Malaysia",
      "continent": "Asia",
      "population": 3.2406372E7,
      "totalCases": 9038.0,
      "totalDeaths": 125.0,
      "totalRecovered": 8713.0,
      "activeCases": 200.0,
      "critical": 2.0,
      "totalCases1M": 279.0,
      "deaths1M": 4.0,
      "totalTests": 991333.0,
      "tests1M": 30591.0
    },
    {
      "country": "Tajikistan",
      "continent": "Asia",
      "population": 9557468.0,
      "totalCases": 7665.0,
      "totalDeaths": 62.0,
      "totalRecovered": 6443.0,
      "activeCases": 1160.0,
      "totalCases1M": 802.0,
      "deaths1M": 6.0
    },
    {
      "country": "Lebanon",
      "continent": "Asia",
      "population": 6822220.0,
      "totalCases": 5672.0,
      "totalDeaths": 70.0,
      "totalRecovered": 1974.0,
      "activeCases": 3628.0,
      "critical": 46.0,
      "totalCases1M": 831.0,
      "deaths1M": 10.0,
      "totalTests": 345268.0,
      "tests1M": 50609.0
    },
    {
      "country": "Maldives",
      "continent": "Asia",
      "population": 541448.0,
      "totalCases": 4680.0,
      "totalDeaths": 19.0,
      "totalRecovered": 2725.0,
      "activeCases": 1936.0,
      "critical": 12.0,
      "totalCases1M": 8643.0,
      "deaths1M": 35.0,
      "totalTests": 85587.0,
      "tests1M": 158071.0
    },
    {
      "country": "Hong Kong",
      "continent": "Asia",
      "population": 7503041.0,
      "totalCases": 3850.0,
      "totalDeaths": 46.0,
      "totalRecovered": 2458.0,
      "activeCases": 1346.0,
      "critical": 39.0,
      "totalCases1M": 513.0,
      "deaths1M": 6.0,
      "totalTests": 692430.0,
      "tests1M": 92287.0
    },
    {
      "country": "Thailand",
      "continent": "Asia",
      "population": 6.9817894E7,
      "totalCases": 3330.0,
      "totalDeaths": 58.0,
      "totalRecovered": 3148.0,
      "activeCases": 124.0,
      "critical": 1.0,
      "totalCases1M": 48.0,
      "deaths1M": 0.8,
      "totalTests": 749213.0,
      "tests1M": 10731.0
    },
    {
      "country": "Sri Lanka",
      "continent": "Asia",
      "population": 2.1422362E7,
      "totalCases": 2839.0,
      "totalDeaths": 11.0,
      "totalRecovered": 2541.0,
      "activeCases": 287.0,
      "critical": 1.0,
      "totalCases1M": 133.0,
      "deaths1M": 0.5,
      "totalTests": 166737.0,
      "tests1M": 7783.0
    },
    {
      "country": "Yemen",
      "continent": "Asia",
      "population": 2.9886897E7,
      "totalCases": 1768.0,
      "totalDeaths": 508.0,
      "totalRecovered": 898.0,
      "activeCases": 362.0,
      "totalCases1M": 59.0,
      "deaths1M": 17.0,
      "totalTests": 120.0,
      "tests1M": 4.0
    },
    {
      "country": "Jordan",
      "continent": "Asia",
      "population": 1.0213138E7,
      "totalCases": 1232.0,
      "totalDeaths": 11.0,
      "totalRecovered": 1171.0,
      "activeCases": 50.0,
      "critical": 3.0,
      "totalCases1M": 121.0,
      "deaths1M": 1.0,
      "totalTests": 628745.0,
      "tests1M": 61562.0
    },
    {
      "country": "Cyprus",
      "continent": "Asia",
      "population": 1208238.0,
      "totalCases": 1208.0,
      "totalDeaths": 19.0,
      "totalRecovered": 856.0,
      "activeCases": 333.0,
      "totalCases1M": 1000.0,
      "deaths1M": 16.0,
      "totalTests": 216597.0,
      "tests1M": 179267.0
    },
    {
      "country": "Georgia",
      "continent": "Asia",
      "population": 3988368.0,
      "totalCases": 1206.0,
      "totalDeaths": 17.0,
      "totalRecovered": 987.0,
      "activeCases": 202.0,
      "totalCases1M": 302.0,
      "deaths1M": 4.0,
      "totalTests": 240473.0,
      "tests1M": 60294.0
    },
    {
      "country": "Syria",
      "continent": "Asia",
      "population": 1.75396E7,
      "totalCases": 999.0,
      "totalDeaths": 48.0,
      "totalRecovered": 311.0,
      "activeCases": 640.0,
      "totalCases1M": 57.0,
      "deaths1M": 3.0
    },
    {
      "country": "Vietnam",
      "continent": "Asia",
      "population": 9.742547E7,
      "totalCases": 747.0,
      "totalDeaths": 10.0,
      "totalRecovered": 392.0,
      "activeCases": 345.0,
      "totalCases1M": 8.0,
      "deaths1M": 0.1,
      "totalTests": 482456.0,
      "tests1M": 4952.0
    },
    {
      "country": "Taiwan",
      "continent": "Asia",
      "population": 2.3821199E7,
      "totalCases": 477.0,
      "totalDeaths": 7.0,
      "totalRecovered": 443.0,
      "activeCases": 27.0,
      "totalCases1M": 20.0,
      "deaths1M": 0.3,
      "totalTests": 82737.0,
      "tests1M": 3473.0
    },
    {
      "country": "Myanmar",
      "continent": "Asia",
      "population": 5.4446389E7,
      "totalCases": 357.0,
      "totalDeaths": 6.0,
      "totalRecovered": 308.0,
      "activeCases": 43.0,
      "totalCases1M": 7.0,
      "deaths1M": 0.1,
      "totalTests": 122290.0,
      "tests1M": 2246.0
    },
    {
      "country": "Mongolia",
      "continent": "Asia",
      "population": 3283344.0,
      "totalCases": 293.0,
      "totalRecovered": 260.0,
      "activeCases": 33.0,
      "critical": 1.0,
      "totalCases1M": 89.0,
      "totalTests": 38334.0,
      "tests1M": 11675.0
    },
    {
      "country": "Cambodia",
      "continent": "Asia",
      "population": 1.6741375E7,
      "totalCases": 243.0,
      "totalRecovered": 210.0,
      "activeCases": 33.0,
      "critical": 1.0,
      "totalCases1M": 15.0,
      "totalTests": 67807.0,
      "tests1M": 4050.0
    },
    {
      "country": "Brunei ",
      "continent": "Asia",
      "population": 437893.0,
      "totalCases": 141.0,
      "totalDeaths": 3.0,
      "totalRecovered": 138.0,
      "activeCases": 0.0,
      "totalCases1M": 322.0,
      "deaths1M": 7.0,
      "totalTests": 41148.0,
      "tests1M": 93968.0
    },
    {
      "country": "Bhutan",
      "continent": "Asia",
      "population": 772443.0,
      "totalCases": 105.0,
      "totalRecovered": 93.0,
      "activeCases": 12.0,
      "totalCases1M": 136.0,
      "totalTests": 54589.0,
      "tests1M": 70671.0
    },
    {
      "country": "Macao",
      "continent": "Asia",
      "population": 650193.0,
      "totalCases": 46.0,
      "totalRecovered": 46.0,
      "activeCases": 0.0,
      "totalCases1M": 71.0,
      "totalTests": 4071.0,
      "tests1M": 6261.0
    },
    {
      "country": "Timor-Leste",
      "continent": "Asia",
      "population": 1320812.0,
      "totalCases": 25.0,
      "totalRecovered": 24.0,
      "activeCases": 1.0,
      "totalCases1M": 19.0,
      "totalTests": 4238.0,
      "tests1M": 3209.0
    },
    {
      "country": "Laos",
      "continent": "Asia",
      "population": 7285750.0,
      "totalCases": 20.0,
      "totalRecovered": 19.0,
      "activeCases": 1.0,
      "totalCases1M": 3.0,
      "totalTests": 29374.0,
      "tests1M": 4032.0
    }
  ],
  "Europe": [
    {
      "country": "Russia",
      "continent": "Europe",
      "population": 1.45940924E8,
      "totalCases": 871894.0,
      "totalDeaths": 14606.0,
      "totalRecovered": 676357.0,
      "activeCases": 180931.0,
      "critical": 2300.0,
      "totalCases1M": 5974.0,
      "deaths1M": 100.0,
      "totalTests": 2.9716907E7,
      "tests1M": 203623.0
    },
    {
      "country": "Spain",
      "continent": "Europe",
      "population": 4.6756648E7,
      "totalCases": 354530.0,
      "totalDeaths": 28500.0,
      "critical": 617.0,
      "totalCases1M": 7582.0,
      "deaths1M": 610.0,
      "totalTests": 7064329.0,
      "tests1M": 151087.0
    },
    {
      "country": "UK",
      "continent": "Europe",
      "population": 6.7922029E7,
      "totalCases": 308134.0,
      "totalDeaths": 46413.0,
      "critical": 73.0,
      "totalCases1M": 4537.0,
      "deaths1M": 683.0,
      "totalTests": 1.7515234E7,
      "tests1M": 257873.0
    },
    {
      "country": "Italy",
      "continent": "Europe",
      "population": 6.0452568E7,
      "totalCases": 249204.0,
      "totalDeaths": 35187.0,
      "totalRecovered": 201323.0,
      "activeCases": 12694.0,
      "critical": 42.0,
      "totalCases1M": 4122.0,
      "deaths1M": 582.0,
      "totalTests": 7099713.0,
      "tests1M": 117443.0
    },
    {
      "country": "Germany",
      "continent": "Europe",
      "population": 8.381126E7,
      "totalCases": 215210.0,
      "totalDeaths": 9252.0,
      "totalRecovered": 196200.0,
      "activeCases": 9758.0,
      "critical": 236.0,
      "totalCases1M": 2568.0,
      "deaths1M": 110.0,
      "totalTests": 8586648.0,
      "tests1M": 102452.0
    },
    {
      "country": "France",
      "continent": "Europe",
      "population": 6.5288306E7,
      "totalCases": 195633.0,
      "totalDeaths": 30312.0,
      "totalRecovered": 82460.0,
      "activeCases": 82861.0,
      "critical": 384.0,
      "totalCases1M": 2996.0,
      "deaths1M": 464.0,
      "totalTests": 3992206.0,
      "tests1M": 61147.0
    },
    {
      "country": "Sweden",
      "continent": "Europe",
      "population": 1.0105596E7,
      "totalCases": 81967.0,
      "totalDeaths": 5766.0,
      "critical": 38.0,
      "totalCases1M": 8111.0,
      "deaths1M": 571.0,
      "totalTests": 863315.0,
      "tests1M": 85429.0
    },
    {
      "country": "Ukraine",
      "continent": "Europe",
      "population": 4.3705858E7,
      "totalCases": 76808.0,
      "totalDeaths": 1819.0,
      "totalRecovered": 42524.0,
      "activeCases": 32465.0,
      "critical": 158.0,
      "totalCases1M": 1757.0,
      "deaths1M": 42.0,
      "totalTests": 1116641.0,
      "tests1M": 25549.0
    },
    {
      "country": "Belgium",
      "continent": "Europe",
      "population": 1.1594739E7,
      "totalCases": 71158.0,
      "totalDeaths": 9859.0,
      "totalRecovered": 17661.0,
      "activeCases": 43638.0,
      "critical": 61.0,
      "totalCases1M": 6137.0,
      "deaths1M": 850.0,
      "totalTests": 1767120.0,
      "tests1M": 152407.0
    },
    {
      "country": "Belarus",
      "continent": "Europe",
      "population": 9449001.0,
      "totalCases": 68503.0,
      "totalDeaths": 580.0,
      "totalRecovered": 63756.0,
      "activeCases": 4167.0,
      "totalCases1M": 7250.0,
      "deaths1M": 61.0,
      "totalTests": 1344303.0,
      "tests1M": 142269.0
    },
    {
      "country": "Romania",
      "continent": "Europe",
      "population": 1.9224023E7,
      "totalCases": 57895.0,
      "totalDeaths": 2566.0,
      "totalRecovered": 28992.0,
      "activeCases": 26337.0,
      "critical": 458.0,
      "totalCases1M": 3012.0,
      "deaths1M": 133.0,
      "totalTests": 1319369.0,
      "tests1M": 68631.0
    },
    {
      "country": "Netherlands",
      "continent": "Europe",
      "population": 1.7138756E7,
      "totalCases": 56982.0,
      "totalDeaths": 6153.0,
      "critical": 37.0,
      "totalCases1M": 3325.0,
      "deaths1M": 359.0,
      "totalTests": 1079860.0,
      "tests1M": 63007.0
    },
    {
      "country": "Portugal",
      "continent": "Europe",
      "population": 1.0193593E7,
      "totalCases": 52061.0,
      "totalDeaths": 1743.0,
      "totalRecovered": 37840.0,
      "activeCases": 12478.0,
      "critical": 42.0,
      "totalCases1M": 5107.0,
      "deaths1M": 171.0,
      "totalTests": 1705474.0,
      "tests1M": 167308.0
    },
    {
      "country": "Poland",
      "continent": "Europe",
      "population": 3.7842302E7,
      "totalCases": 49515.0,
      "totalDeaths": 1774.0,
      "totalRecovered": 35642.0,
      "activeCases": 12099.0,
      "critical": 72.0,
      "totalCases1M": 1308.0,
      "deaths1M": 47.0,
      "totalTests": 2374686.0,
      "tests1M": 62752.0
    },
    {
      "country": "Switzerland",
      "continent": "Europe",
      "population": 8660952.0,
      "totalCases": 36108.0,
      "totalDeaths": 1985.0,
      "totalRecovered": 31600.0,
      "activeCases": 2523.0,
      "critical": 23.0,
      "totalCases1M": 4169.0,
      "deaths1M": 229.0,
      "totalTests": 822764.0,
      "tests1M": 94997.0
    },
    {
      "country": "Serbia",
      "continent": "Europe",
      "population": 8733665.0,
      "totalCases": 27332.0,
      "totalDeaths": 621.0,
      "totalRecovered": 14047.0,
      "activeCases": 12664.0,
      "critical": 120.0,
      "totalCases1M": 3129.0,
      "deaths1M": 71.0,
      "totalTests": 723137.0,
      "tests1M": 82799.0
    },
    {
      "country": "Moldova",
      "continent": "Europe",
      "population": 4032983.0,
      "totalCases": 26628.0,
      "totalDeaths": 828.0,
      "totalRecovered": 18676.0,
      "activeCases": 7124.0,
      "critical": 362.0,
      "totalCases1M": 6603.0,
      "deaths1M": 205.0,
      "totalTests": 128076.0,
      "tests1M": 31757.0
    },
    {
      "country": "Ireland",
      "continent": "Europe",
      "population": 4943200.0,
      "totalCases": 26372.0,
      "totalDeaths": 1768.0,
      "totalRecovered": 23364.0,
      "activeCases": 1240.0,
      "critical": 5.0,
      "totalCases1M": 5335.0,
      "deaths1M": 358.0,
      "totalTests": 652917.0,
      "tests1M": 132084.0
    },
    {
      "country": "Austria",
      "continent": "Europe",
      "population": 9011577.0,
      "totalCases": 21696.0,
      "totalDeaths": 719.0,
      "totalRecovered": 19596.0,
      "activeCases": 1381.0,
      "critical": 25.0,
      "totalCases1M": 2408.0,
      "deaths1M": 80.0,
      "totalTests": 937275.0,
      "tests1M": 104008.0
    },
    {
      "country": "Czechia",
      "continent": "Europe",
      "population": 1.0711019E7,
      "totalCases": 17731.0,
      "totalDeaths": 390.0,
      "totalRecovered": 12320.0,
      "activeCases": 5021.0,
      "critical": 17.0,
      "totalCases1M": 1655.0,
      "deaths1M": 36.0,
      "totalTests": 728670.0,
      "tests1M": 68030.0
    },
    {
      "country": "Denmark",
      "continent": "Europe",
      "population": 5794279.0,
      "totalCases": 14306.0,
      "totalDeaths": 617.0,
      "totalRecovered": 12787.0,
      "activeCases": 902.0,
      "critical": 2.0,
      "totalCases1M": 2469.0,
      "deaths1M": 106.0,
      "totalTests": 1654512.0,
      "tests1M": 285542.0
    },
    {
      "country": "Bosnia and Herzegovina",
      "continent": "Europe",
      "population": 3278650.0,
      "totalCases": 13396.0,
      "totalDeaths": 384.0,
      "totalRecovered": 7042.0,
      "activeCases": 5970.0,
      "totalCases1M": 4086.0,
      "deaths1M": 117.0,
      "totalTests": 147021.0,
      "tests1M": 44842.0
    },
    {
      "country": "Bulgaria",
      "continent": "Europe",
      "population": 6942854.0,
      "totalCases": 13014.0,
      "totalDeaths": 435.0,
      "totalRecovered": 7374.0,
      "activeCases": 5205.0,
      "critical": 47.0,
      "totalCases1M": 1874.0,
      "deaths1M": 63.0,
      "totalTests": 294087.0,
      "tests1M": 42358.0
    },
    {
      "country": "North Macedonia",
      "continent": "Europe",
      "population": 2083365.0,
      "totalCases": 11399.0,
      "totalDeaths": 517.0,
      "totalRecovered": 7480.0,
      "activeCases": 3402.0,
      "critical": 3.0,
      "totalCases1M": 5471.0,
      "deaths1M": 248.0,
      "totalTests": 109946.0,
      "tests1M": 52773.0
    },
    {
      "country": "Norway",
      "continent": "Europe",
      "population": 5425471.0,
      "totalCases": 9468.0,
      "totalDeaths": 256.0,
      "totalRecovered": 8857.0,
      "activeCases": 355.0,
      "critical": 3.0,
      "totalCases1M": 1745.0,
      "deaths1M": 47.0,
      "totalTests": 472841.0,
      "tests1M": 87152.0
    },
    {
      "country": "Finland",
      "continent": "Europe",
      "population": 5541604.0,
      "totalCases": 7532.0,
      "totalDeaths": 331.0,
      "totalRecovered": 6980.0,
      "activeCases": 221.0,
      "totalCases1M": 1359.0,
      "deaths1M": 60.0,
      "totalTests": 389500.0,
      "tests1M": 70287.0
    },
    {
      "country": "Luxembourg",
      "continent": "Europe",
      "population": 626952.0,
      "totalCases": 7073.0,
      "totalDeaths": 119.0,
      "totalRecovered": 5750.0,
      "activeCases": 1204.0,
      "critical": 9.0,
      "totalCases1M": 11282.0,
      "deaths1M": 190.0,
      "totalTests": 623994.0,
      "tests1M": 995282.0
    },
    {
      "country": "Albania",
      "continent": "Europe",
      "population": 2877470.0,
      "totalCases": 6016.0,
      "totalDeaths": 188.0,
      "totalRecovered": 3155.0,
      "activeCases": 2673.0,
      "critical": 23.0,
      "totalCases1M": 2091.0,
      "deaths1M": 65.0,
      "totalTests": 38997.0,
      "tests1M": 13553.0
    },
    {
      "country": "Croatia",
      "continent": "Europe",
      "population": 4102577.0,
      "totalCases": 5404.0,
      "totalDeaths": 155.0,
      "totalRecovered": 4688.0,
      "activeCases": 561.0,
      "critical": 7.0,
      "totalCases1M": 1317.0,
      "deaths1M": 38.0,
      "totalTests": 125317.0,
      "tests1M": 30546.0
    },
    {
      "country": "Greece",
      "continent": "Europe",
      "population": 1.0417673E7,
      "totalCases": 5123.0,
      "totalDeaths": 210.0,
      "totalRecovered": 1374.0,
      "activeCases": 3539.0,
      "critical": 14.0,
      "totalCases1M": 492.0,
      "deaths1M": 20.0,
      "totalTests": 619393.0,
      "tests1M": 59456.0
    },
    {
      "country": "Hungary",
      "continent": "Europe",
      "population": 9657785.0,
      "totalCases": 4597.0,
      "totalDeaths": 600.0,
      "totalRecovered": 3463.0,
      "activeCases": 534.0,
      "critical": 8.0,
      "totalCases1M": 476.0,
      "deaths1M": 62.0,
      "totalTests": 352546.0,
      "tests1M": 36504.0
    },
    {
      "country": "Montenegro",
      "continent": "Europe",
      "population": 628074.0,
      "totalCases": 3480.0,
      "totalDeaths": 60.0,
      "totalRecovered": 2178.0,
      "activeCases": 1242.0,
      "totalCases1M": 5541.0,
      "deaths1M": 96.0,
      "totalTests": 38427.0,
      "tests1M": 61182.0
    },
    {
      "country": "Slovakia",
      "continent": "Europe",
      "population": 5459915.0,
      "totalCases": 2480.0,
      "totalDeaths": 29.0,
      "totalRecovered": 1824.0,
      "activeCases": 627.0,
      "critical": 2.0,
      "totalCases1M": 454.0,
      "deaths1M": 5.0,
      "totalTests": 272322.0,
      "tests1M": 49877.0
    },
    {
      "country": "Slovenia",
      "continent": "Europe",
      "population": 2078968.0,
      "totalCases": 2223.0,
      "totalDeaths": 125.0,
      "totalRecovered": 1909.0,
      "activeCases": 189.0,
      "critical": 2.0,
      "totalCases1M": 1069.0,
      "deaths1M": 60.0,
      "totalTests": 135702.0,
      "tests1M": 65274.0
    },
    {
      "country": "Lithuania",
      "continent": "Europe",
      "population": 2718121.0,
      "totalCases": 2171.0,
      "totalDeaths": 81.0,
      "totalRecovered": 1656.0,
      "activeCases": 434.0,
      "critical": 6.0,
      "totalCases1M": 799.0,
      "deaths1M": 30.0,
      "totalTests": 540784.0,
      "tests1M": 198955.0
    },
    {
      "country": "Estonia",
      "continent": "Europe",
      "population": 1326627.0,
      "totalCases": 2124.0,
      "totalDeaths": 63.0,
      "totalRecovered": 1954.0,
      "activeCases": 107.0,
      "totalCases1M": 1601.0,
      "deaths1M": 47.0,
      "totalTests": 122880.0,
      "tests1M": 92626.0
    },
    {
      "country": "Iceland",
      "continent": "Europe",
      "population": 341465.0,
      "totalCases": 1930.0,
      "totalDeaths": 10.0,
      "totalRecovered": 1825.0,
      "activeCases": 95.0,
      "totalCases1M": 5652.0,
      "deaths1M": 29.0,
      "totalTests": 149693.0,
      "tests1M": 438385.0
    },
    {
      "country": "Latvia",
      "continent": "Europe",
      "population": 1883936.0,
      "totalCases": 1275.0,
      "totalDeaths": 32.0,
      "totalRecovered": 1070.0,
      "activeCases": 173.0,
      "totalCases1M": 677.0,
      "deaths1M": 17.0,
      "totalTests": 207909.0,
      "tests1M": 110359.0
    },
    {
      "country": "Malta",
      "continent": "Europe",
      "population": 441663.0,
      "totalCases": 946.0,
      "totalDeaths": 9.0,
      "totalRecovered": 670.0,
      "activeCases": 267.0,
      "totalCases1M": 2142.0,
      "deaths1M": 20.0,
      "totalTests": 136713.0,
      "tests1M": 309541.0
    },
    {
      "country": "Andorra",
      "continent": "Europe",
      "population": 77278.0,
      "totalCases": 944.0,
      "totalDeaths": 52.0,
      "totalRecovered": 828.0,
      "activeCases": 64.0,
      "critical": 1.0,
      "totalCases1M": 12216.0,
      "deaths1M": 673.0,
      "totalTests": 3750.0,
      "tests1M": 48526.0
    },
    {
      "country": "San Marino",
      "continent": "Europe",
      "population": 33938.0,
      "totalCases": 699.0,
      "totalDeaths": 42.0,
      "totalRecovered": 657.0,
      "activeCases": 0.0,
      "totalCases1M": 20596.0,
      "deaths1M": 1238.0,
      "totalTests": 6068.0,
      "tests1M": 178797.0
    },
    {
      "country": "Channel Islands",
      "continent": "Europe",
      "population": 174022.0,
      "totalCases": 597.0,
      "totalDeaths": 47.0,
      "totalRecovered": 533.0,
      "activeCases": 17.0,
      "totalCases1M": 3431.0,
      "deaths1M": 270.0,
      "totalTests": 30721.0,
      "tests1M": 176535.0
    },
    {
      "country": "Isle of Man",
      "continent": "Europe",
      "population": 85078.0,
      "totalCases": 336.0,
      "totalDeaths": 24.0,
      "totalRecovered": 312.0,
      "activeCases": 0.0,
      "totalCases1M": 3949.0,
      "deaths1M": 282.0,
      "totalTests": 8627.0,
      "tests1M": 101401.0
    },
    {
      "country": "Faeroe Islands",
      "continent": "Europe",
      "population": 48882.0,
      "totalCases": 266.0,
      "totalRecovered": 192.0,
      "activeCases": 74.0,
      "critical": 1.0,
      "totalCases1M": 5442.0,
      "totalTests": 43045.0,
      "tests1M": 880590.0
    },
    {
      "country": "Gibraltar",
      "continent": "Europe",
      "population": 33690.0,
      "totalCases": 190.0,
      "totalRecovered": 184.0,
      "activeCases": 6.0,
      "totalCases1M": 5640.0,
      "totalTests": 23063.0,
      "tests1M": 684565.0
    },
    {
      "country": "Monaco",
      "continent": "Europe",
      "population": 39270.0,
      "totalCases": 125.0,
      "totalDeaths": 4.0,
      "totalRecovered": 105.0,
      "activeCases": 16.0,
      "critical": 2.0,
      "totalCases1M": 3183.0,
      "deaths1M": 102.0,
      "totalTests": 38209.0,
      "tests1M": 972982.0
    },
    {
      "country": "Liechtenstein",
      "continent": "Europe",
      "population": 38139.0,
      "totalCases": 89.0,
      "totalDeaths": 1.0,
      "totalRecovered": 85.0,
      "activeCases": 3.0,
      "totalCases1M": 2334.0,
      "deaths1M": 26.0,
      "totalTests": 900.0,
      "tests1M": 23598.0
    },
    {
      "country": "Vatican City",
      "continent": "Europe",
      "population": 801.0,
      "totalCases": 12.0,
      "totalRecovered": 12.0,
      "activeCases": 0.0,
      "totalCases1M": 14981.0
    }
  ],
  "Africa": [
    {
      "country": "South Africa",
      "continent": "Africa",
      "population": 5.9381566E7,
      "totalCases": 538184.0,
      "totalDeaths": 9604.0,
      "totalRecovered": 387316.0,
      "activeCases": 141264.0,
      "critical": 539.0,
      "totalCases1M": 9063.0,
      "deaths1M": 162.0,
      "totalTests": 3149807.0,
      "tests1M": 53044.0
    },
    {
      "country": "Egypt",
      "continent": "Africa",
      "population": 1.02516525E8,
      "totalCases": 95006.0,
      "totalDeaths": 4951.0,
      "totalRecovered": 48898.0,
      "activeCases": 41157.0,
      "critical": 41.0,
      "totalCases1M": 927.0,
      "deaths1M": 48.0,
      "totalTests": 135000.0,
      "tests1M": 1317.0
    },
    {
      "country": "Nigeria",
      "continent": "Africa",
      "population": 2.066063E8,
      "totalCases": 45244.0,
      "totalDeaths": 930.0,
      "totalRecovered": 32430.0,
      "activeCases": 11884.0,
      "critical": 7.0,
      "totalCases1M": 219.0,
      "deaths1M": 5.0,
      "totalTests": 306894.0,
      "tests1M": 1485.0
    },
    {
      "country": "Ghana",
      "continent": "Africa",
      "population": 3.1133483E7,
      "totalCases": 39642.0,
      "totalDeaths": 199.0,
      "totalRecovered": 36384.0,
      "activeCases": 3059.0,
      "critical": 7.0,
      "totalCases1M": 1273.0,
      "deaths1M": 6.0,
      "totalTests": 405817.0,
      "tests1M": 13035.0
    },
    {
      "country": "Algeria",
      "continent": "Africa",
      "population": 4.3926079E7,
      "totalCases": 33626.0,
      "totalDeaths": 1273.0,
      "totalRecovered": 23238.0,
      "activeCases": 9115.0,
      "critical": 57.0,
      "totalCases1M": 766.0,
      "deaths1M": 29.0
    },
    {
      "country": "Morocco",
      "continent": "Africa",
      "population": 3.6953359E7,
      "totalCases": 29644.0,
      "totalDeaths": 449.0,
      "totalRecovered": 20553.0,
      "activeCases": 8642.0,
      "critical": 31.0,
      "totalCases1M": 802.0,
      "deaths1M": 12.0,
      "totalTests": 1383816.0,
      "tests1M": 37448.0
    },
    {
      "country": "Kenya",
      "continent": "Africa",
      "population": 5.388116E7,
      "totalCases": 24411.0,
      "totalDeaths": 399.0,
      "totalRecovered": 10444.0,
      "activeCases": 13568.0,
      "critical": 44.0,
      "totalCases1M": 453.0,
      "deaths1M": 7.0,
      "totalTests": 335318.0,
      "tests1M": 6223.0
    },
    {
      "country": "Ethiopia",
      "continent": "Africa",
      "population": 1.15223736E8,
      "totalCases": 20900.0,
      "totalDeaths": 365.0,
      "totalRecovered": 9027.0,
      "activeCases": 11508.0,
      "critical": 185.0,
      "totalCases1M": 181.0,
      "deaths1M": 3.0,
      "totalTests": 468814.0,
      "tests1M": 4069.0
    },
    {
      "country": "Cameroon",
      "continent": "Africa",
      "population": 2.6606188E7,
      "totalCases": 17718.0,
      "totalDeaths": 391.0,
      "totalRecovered": 15320.0,
      "activeCases": 2007.0,
      "critical": 30.0,
      "totalCases1M": 666.0,
      "deaths1M": 15.0,
      "totalTests": 149000.0,
      "tests1M": 5600.0
    },
    {
      "country": "Ivory Coast",
      "continent": "Africa",
      "population": 2.643795E7,
      "totalCases": 16447.0,
      "totalDeaths": 103.0,
      "totalRecovered": 12484.0,
      "activeCases": 3860.0,
      "totalCases1M": 622.0,
      "deaths1M": 4.0,
      "totalTests": 104584.0,
      "tests1M": 3956.0
    },
    {
      "country": "Madagascar",
      "continent": "Africa",
      "population": 2.7755708E7,
      "totalCases": 12526.0,
      "totalDeaths": 134.0,
      "totalRecovered": 10148.0,
      "activeCases": 2244.0,
      "critical": 88.0,
      "totalCases1M": 451.0,
      "deaths1M": 5.0,
      "totalTests": 46301.0,
      "tests1M": 1668.0
    },
    {
      "country": "Sudan",
      "continent": "Africa",
      "population": 4.3943536E7,
      "totalCases": 11780.0,
      "totalDeaths": 763.0,
      "totalRecovered": 6194.0,
      "activeCases": 4823.0,
      "totalCases1M": 268.0,
      "deaths1M": 17.0,
      "totalTests": 401.0,
      "tests1M": 9.0
    },
    {
      "country": "Senegal",
      "continent": "Africa",
      "population": 1.6783877E7,
      "totalCases": 10715.0,
      "totalDeaths": 223.0,
      "totalRecovered": 7101.0,
      "activeCases": 3391.0,
      "critical": 33.0,
      "totalCases1M": 638.0,
      "deaths1M": 13.0,
      "totalTests": 114761.0,
      "tests1M": 6838.0
    },
    {
      "country": "DRC",
      "continent": "Africa",
      "population": 8.9802183E7,
      "totalCases": 9309.0,
      "totalDeaths": 215.0,
      "totalRecovered": 8048.0,
      "activeCases": 1046.0,
      "totalCases1M": 104.0,
      "deaths1M": 2.0
    },
    {
      "country": "Gabon",
      "continent": "Africa",
      "population": 2230563.0,
      "totalCases": 7787.0,
      "totalDeaths": 51.0,
      "totalRecovered": 5609.0,
      "activeCases": 2127.0,
      "critical": 11.0,
      "totalCases1M": 3491.0,
      "deaths1M": 23.0,
      "totalTests": 85369.0,
      "tests1M": 38272.0
    },
    {
      "country": "Guinea",
      "continent": "Africa",
      "population": 1.3164905E7,
      "totalCases": 7664.0,
      "totalDeaths": 49.0,
      "totalRecovered": 6757.0,
      "activeCases": 858.0,
      "critical": 24.0,
      "totalCases1M": 582.0,
      "deaths1M": 4.0,
      "totalTests": 14407.0,
      "tests1M": 1094.0
    },
    {
      "country": "Zambia",
      "continent": "Africa",
      "population": 1.8430129E7,
      "totalCases": 7164.0,
      "totalDeaths": 199.0,
      "totalRecovered": 5786.0,
      "activeCases": 1179.0,
      "totalCases1M": 389.0,
      "deaths1M": 11.0,
      "totalTests": 90307.0,
      "tests1M": 4900.0
    },
    {
      "country": "Mauritania",
      "continent": "Africa",
      "population": 4660728.0,
      "totalCases": 6444.0,
      "totalDeaths": 157.0,
      "totalRecovered": 5291.0,
      "activeCases": 996.0,
      "critical": 3.0,
      "totalCases1M": 1383.0,
      "deaths1M": 34.0,
      "totalTests": 57387.0,
      "tests1M": 12313.0
    },
    {
      "country": "Djibouti",
      "continent": "Africa",
      "population": 989387.0,
      "totalCases": 5330.0,
      "totalDeaths": 59.0,
      "totalRecovered": 5057.0,
      "activeCases": 214.0,
      "totalCases1M": 5387.0,
      "deaths1M": 60.0,
      "totalTests": 59909.0,
      "tests1M": 60552.0
    },
    {
      "country": "Libya",
      "continent": "Africa",
      "population": 6880353.0,
      "totalCases": 4879.0,
      "totalDeaths": 107.0,
      "totalRecovered": 652.0,
      "activeCases": 4120.0,
      "totalCases1M": 709.0,
      "deaths1M": 16.0,
      "totalTests": 59699.0,
      "tests1M": 8677.0
    },
    {
      "country": "Equatorial Guinea",
      "continent": "Africa",
      "population": 1407001.0,
      "totalCases": 4821.0,
      "totalDeaths": 83.0,
      "totalRecovered": 2182.0,
      "activeCases": 2556.0,
      "totalCases1M": 3426.0,
      "deaths1M": 59.0,
      "totalTests": 44356.0,
      "tests1M": 31525.0
    },
    {
      "country": "CAR",
      "continent": "Africa",
      "population": 4837752.0,
      "totalCases": 4620.0,
      "totalDeaths": 59.0,
      "totalRecovered": 1641.0,
      "activeCases": 2920.0,
      "critical": 2.0,
      "totalCases1M": 955.0,
      "deaths1M": 12.0,
      "totalTests": 29589.0,
      "tests1M": 6116.0
    },
    {
      "country": "Malawi",
      "continent": "Africa",
      "population": 1.9174839E7,
      "totalCases": 4491.0,
      "totalDeaths": 137.0,
      "totalRecovered": 2137.0,
      "activeCases": 2217.0,
      "critical": 4.0,
      "totalCases1M": 234.0,
      "deaths1M": 7.0,
      "totalTests": 33466.0,
      "tests1M": 1745.0
    },
    {
      "country": "Zimbabwe",
      "continent": "Africa",
      "population": 1.4883803E7,
      "totalCases": 4339.0,
      "totalDeaths": 84.0,
      "totalRecovered": 1264.0,
      "activeCases": 2991.0,
      "totalCases1M": 292.0,
      "deaths1M": 6.0,
      "totalTests": 140421.0,
      "tests1M": 9434.0
    },
    {
      "country": "Congo",
      "continent": "Africa",
      "population": 5530506.0,
      "totalCases": 3546.0,
      "totalDeaths": 58.0,
      "totalRecovered": 1589.0,
      "activeCases": 1899.0,
      "totalCases1M": 641.0,
      "deaths1M": 10.0
    },
    {
      "country": "Somalia",
      "continent": "Africa",
      "population": 1.5933012E7,
      "totalCases": 3227.0,
      "totalDeaths": 93.0,
      "totalRecovered": 1728.0,
      "activeCases": 1406.0,
      "critical": 2.0,
      "totalCases1M": 203.0,
      "deaths1M": 6.0
    },
    {
      "country": "Mayotte",
      "continent": "Africa",
      "population": 273419.0,
      "totalCases": 3042.0,
      "totalDeaths": 39.0,
      "totalRecovered": 2738.0,
      "activeCases": 265.0,
      "critical": 2.0,
      "totalCases1M": 11126.0,
      "deaths1M": 143.0,
      "totalTests": 13000.0,
      "tests1M": 47546.0
    },
    {
      "country": "Eswatini",
      "continent": "Africa",
      "population": 1161348.0,
      "totalCases": 2968.0,
      "totalDeaths": 55.0,
      "totalRecovered": 1476.0,
      "activeCases": 1437.0,
      "critical": 5.0,
      "totalCases1M": 2556.0,
      "deaths1M": 47.0,
      "totalTests": 20784.0,
      "tests1M": 17896.0
    },
    {
      "country": "Cabo Verde",
      "continent": "Africa",
      "population": 556581.0,
      "totalCases": 2734.0,
      "totalDeaths": 27.0,
      "totalRecovered": 2010.0,
      "activeCases": 697.0,
      "totalCases1M": 4912.0,
      "deaths1M": 49.0,
      "totalTests": 61633.0,
      "tests1M": 110735.0
    },
    {
      "country": "Namibia",
      "continent": "Africa",
      "population": 2545264.0,
      "totalCases": 2652.0,
      "totalDeaths": 15.0,
      "totalRecovered": 563.0,
      "activeCases": 2074.0,
      "critical": 24.0,
      "totalCases1M": 1042.0,
      "deaths1M": 6.0,
      "totalTests": 29233.0,
      "tests1M": 11485.0
    },
    {
      "country": "Mali",
      "continent": "Africa",
      "population": 2.0302901E7,
      "totalCases": 2552.0,
      "totalDeaths": 124.0,
      "totalRecovered": 1954.0,
      "activeCases": 474.0,
      "totalCases1M": 126.0,
      "deaths1M": 6.0,
      "totalTests": 25152.0,
      "tests1M": 1239.0
    },
    {
      "country": "South Sudan",
      "continent": "Africa",
      "population": 1.1206572E7,
      "totalCases": 2450.0,
      "totalDeaths": 47.0,
      "totalRecovered": 1175.0,
      "activeCases": 1228.0,
      "totalCases1M": 219.0,
      "deaths1M": 4.0,
      "totalTests": 12044.0,
      "tests1M": 1075.0
    },
    {
      "country": "Mozambique",
      "continent": "Africa",
      "population": 3.1333962E7,
      "totalCases": 2120.0,
      "totalDeaths": 15.0,
      "totalRecovered": 795.0,
      "activeCases": 1310.0,
      "totalCases1M": 68.0,
      "deaths1M": 0.5,
      "totalTests": 65151.0,
      "tests1M": 2079.0
    },
    {
      "country": "Rwanda",
      "continent": "Africa",
      "population": 1.2981546E7,
      "totalCases": 2111.0,
      "totalDeaths": 5.0,
      "totalRecovered": 1258.0,
      "activeCases": 848.0,
      "totalCases1M": 163.0,
      "deaths1M": 0.4,
      "totalTests": 286251.0,
      "tests1M": 22051.0
    },
    {
      "country": "Guinea-Bissau",
      "continent": "Africa",
      "population": 1972277.0,
      "totalCases": 2032.0,
      "totalDeaths": 27.0,
      "totalRecovered": 944.0,
      "activeCases": 1061.0,
      "critical": 5.0,
      "totalCases1M": 1030.0,
      "deaths1M": 14.0,
      "totalTests": 1500.0,
      "tests1M": 761.0
    },
    {
      "country": "Benin",
      "continent": "Africa",
      "population": 1.2151976E7,
      "totalCases": 1936.0,
      "totalDeaths": 38.0,
      "totalRecovered": 1600.0,
      "activeCases": 298.0,
      "critical": 1.0,
      "totalCases1M": 159.0,
      "deaths1M": 3.0,
      "totalTests": 93677.0,
      "tests1M": 7709.0
    },
    {
      "country": "Sierra Leone",
      "continent": "Africa",
      "population": 7992169.0,
      "totalCases": 1877.0,
      "totalDeaths": 67.0,
      "totalRecovered": 1427.0,
      "activeCases": 383.0,
      "totalCases1M": 235.0,
      "deaths1M": 8.0
    },
    {
      "country": "Tunisia",
      "continent": "Africa",
      "population": 1.1830801E7,
      "totalCases": 1642.0,
      "totalDeaths": 51.0,
      "totalRecovered": 1241.0,
      "activeCases": 350.0,
      "critical": 9.0,
      "totalCases1M": 139.0,
      "deaths1M": 4.0,
      "totalTests": 100298.0,
      "tests1M": 8478.0
    },
    {
      "country": "Angola",
      "continent": "Africa",
      "population": 3.29563E7,
      "totalCases": 1483.0,
      "totalDeaths": 64.0,
      "totalRecovered": 520.0,
      "activeCases": 899.0,
      "critical": 20.0,
      "totalCases1M": 45.0,
      "deaths1M": 2.0,
      "totalTests": 64747.0,
      "tests1M": 1965.0
    },
    {
      "country": "Liberia",
      "continent": "Africa",
      "population": 5068618.0,
      "totalCases": 1224.0,
      "totalDeaths": 78.0,
      "totalRecovered": 705.0,
      "activeCases": 441.0,
      "totalCases1M": 241.0,
      "deaths1M": 15.0
    },
    {
      "country": "Uganda",
      "continent": "Africa",
      "population": 4.5867852E7,
      "totalCases": 1223.0,
      "totalDeaths": 5.0,
      "totalRecovered": 1102.0,
      "activeCases": 116.0,
      "totalCases1M": 27.0,
      "deaths1M": 0.1,
      "totalTests": 288367.0,
      "tests1M": 6287.0
    },
    {
      "country": "Burkina Faso",
      "continent": "Africa",
      "population": 2.0954852E7,
      "totalCases": 1158.0,
      "totalDeaths": 54.0,
      "totalRecovered": 961.0,
      "activeCases": 143.0,
      "totalCases1M": 55.0,
      "deaths1M": 3.0
    },
    {
      "country": "Niger",
      "continent": "Africa",
      "population": 2.4281433E7,
      "totalCases": 1153.0,
      "totalDeaths": 69.0,
      "totalRecovered": 1057.0,
      "activeCases": 27.0,
      "totalCases1M": 47.0,
      "deaths1M": 3.0,
      "totalTests": 9052.0,
      "tests1M": 373.0
    },
    {
      "country": "Togo",
      "continent": "Africa",
      "population": 8296582.0,
      "totalCases": 1012.0,
      "totalDeaths": 22.0,
      "totalRecovered": 697.0,
      "activeCases": 293.0,
      "critical": 2.0,
      "totalCases1M": 122.0,
      "deaths1M": 3.0,
      "totalTests": 45767.0,
      "tests1M": 5516.0
    },
    {
      "country": "Chad",
      "continent": "Africa",
      "population": 1.6467965E7,
      "totalCases": 942.0,
      "totalDeaths": 76.0,
      "totalRecovered": 838.0,
      "activeCases": 28.0,
      "totalCases1M": 57.0,
      "deaths1M": 5.0
    },
    {
      "country": "Gambia",
      "continent": "Africa",
      "population": 2422754.0,
      "totalCases": 935.0,
      "totalDeaths": 16.0,
      "totalRecovered": 136.0,
      "activeCases": 783.0,
      "totalCases1M": 386.0,
      "deaths1M": 7.0,
      "totalTests": 5183.0,
      "tests1M": 2139.0
    },
    {
      "country": "Sao Tome and Principe",
      "continent": "Africa",
      "population": 219544.0,
      "totalCases": 878.0,
      "totalDeaths": 15.0,
      "totalRecovered": 797.0,
      "activeCases": 66.0,
      "totalCases1M": 3999.0,
      "deaths1M": 68.0,
      "totalTests": 3079.0,
      "tests1M": 14025.0
    },
    {
      "country": "Botswana",
      "continent": "Africa",
      "population": 2356075.0,
      "totalCases": 804.0,
      "totalDeaths": 2.0,
      "totalRecovered": 63.0,
      "activeCases": 739.0,
      "critical": 1.0,
      "totalCases1M": 341.0,
      "deaths1M": 0.8,
      "totalTests": 68423.0,
      "tests1M": 29041.0
    },
    {
      "country": "Lesotho",
      "continent": "Africa",
      "population": 2143943.0,
      "totalCases": 742.0,
      "totalDeaths": 23.0,
      "totalRecovered": 175.0,
      "activeCases": 544.0,
      "totalCases1M": 346.0,
      "deaths1M": 11.0,
      "totalTests": 8771.0,
      "tests1M": 4091.0
    },
    {
      "country": "Runion",
      "continent": "Africa",
      "population": 895952.0,
      "totalCases": 671.0,
      "totalDeaths": 5.0,
      "totalRecovered": 592.0,
      "activeCases": 74.0,
      "critical": 3.0,
      "totalCases1M": 749.0,
      "deaths1M": 6.0,
      "totalTests": 35419.0,
      "tests1M": 39532.0
    },
    {
      "country": "Tanzania",
      "continent": "Africa",
      "population": 5.9886383E7,
      "totalCases": 509.0,
      "totalDeaths": 21.0,
      "totalRecovered": 183.0,
      "activeCases": 305.0,
      "critical": 7.0,
      "totalCases1M": 8.0,
      "deaths1M": 0.4
    },
    {
      "country": "Comoros",
      "continent": "Africa",
      "population": 871326.0,
      "totalCases": 396.0,
      "totalDeaths": 7.0,
      "totalRecovered": 340.0,
      "activeCases": 49.0,
      "totalCases1M": 454.0,
      "deaths1M": 8.0
    },
    {
      "country": "Burundi",
      "continent": "Africa",
      "population": 1.1922216E7,
      "totalCases": 395.0,
      "totalDeaths": 1.0,
      "totalRecovered": 304.0,
      "activeCases": 90.0,
      "totalCases1M": 33.0,
      "deaths1M": 0.08,
      "totalTests": 15614.0,
      "tests1M": 1310.0
    },
    {
      "country": "Mauritius",
      "continent": "Africa",
      "population": 1271985.0,
      "totalCases": 344.0,
      "totalDeaths": 10.0,
      "totalRecovered": 334.0,
      "activeCases": 0.0,
      "totalCases1M": 270.0,
      "deaths1M": 8.0,
      "totalTests": 205285.0,
      "tests1M": 161389.0
    },
    {
      "country": "Eritrea",
      "continent": "Africa",
      "population": 3551175.0,
      "totalCases": 282.0,
      "totalRecovered": 225.0,
      "activeCases": 57.0,
      "totalCases1M": 79.0
    },
    {
      "country": "Seychelles",
      "continent": "Africa",
      "population": 98408.0,
      "totalCases": 126.0,
      "totalRecovered": 124.0,
      "activeCases": 2.0,
      "totalCases1M": 1280.0
    },
    {
      "country": "Western Sahara",
      "continent": "Africa",
      "population": 598682.0,
      "totalCases": 10.0,
      "totalDeaths": 1.0,
      "totalRecovered": 8.0,
      "activeCases": 1.0,
      "totalCases1M": 17.0,
      "deaths1M": 2.0
    }
  ],
  "Australia/Oceania": [
    {
      "country": "Australia",
      "continent": "Australia/Oceania",
      "population": 2.5528864E7,
      "totalCases": 19890.0,
      "totalDeaths": 255.0,
      "totalRecovered": 10941.0,
      "activeCases": 8694.0,
      "critical": 52.0,
      "totalCases1M": 779.0,
      "deaths1M": 10.0,
      "totalTests": 4631419.0,
      "tests1M": 181419.0
    },
    {
      "country": "New Zealand",
      "continent": "Australia/Oceania",
      "population": 5002100.0,
      "totalCases": 1569.0,
      "totalDeaths": 22.0,
      "totalRecovered": 1524.0,
      "activeCases": 23.0,
      "totalCases1M": 314.0,
      "deaths1M": 4.0,
      "totalTests": 486943.0,
      "tests1M": 97348.0
    },
    {
      "country": "Papua New Guinea",
      "continent": "Australia/Oceania",
      "population": 8963009.0,
      "totalCases": 163.0,
      "totalDeaths": 3.0,
      "totalRecovered": 53.0,
      "activeCases": 107.0,
      "totalCases1M": 18.0,
      "deaths1M": 0.3,
      "totalTests": 10808.0,
      "tests1M": 1206.0
    },
    {
      "country": "French Polynesia",
      "continent": "Australia/Oceania",
      "population": 281072.0,
      "totalCases": 64.0,
      "totalRecovered": 62.0,
      "activeCases": 2.0,
      "totalCases1M": 228.0,
      "totalTests": 5849.0,
      "tests1M": 20810.0
    },
    {
      "country": "Fiji",
      "continent": "Australia/Oceania",
      "population": 897095.0,
      "totalCases": 27.0,
      "totalDeaths": 1.0,
      "totalRecovered": 18.0,
      "activeCases": 8.0,
      "totalCases1M": 30.0,
      "deaths1M": 1.0,
      "totalTests": 6693.0,
      "tests1M": 7461.0
    },
    {
      "country": "New Caledonia",
      "continent": "Australia/Oceania",
      "population": 285769.0,
      "totalCases": 22.0,
      "totalRecovered": 22.0,
      "activeCases": 0.0,
      "totalCases1M": 77.0,
      "totalTests": 11099.0,
      "tests1M": 38839.0
    }
  ],
  "North America": [
    {
      "country": "USA",
      "continent": "North America",
      "population": 3.3119813E8,
      "totalCases": 5032179.0,
      "totalDeaths": 162804.0,
      "totalRecovered": 2576668.0,
      "activeCases": 2292707.0,
      "critical": 18296.0,
      "totalCases1M": 15194.0,
      "deaths1M": 492.0,
      "totalTests": 6.3139605E7,
      "tests1M": 190640.0
    },
    {
      "country": "Mexico",
      "continent": "North America",
      "population": 1.2906616E8,
      "totalCases": 462690.0,
      "totalDeaths": 50517.0,
      "totalRecovered": 308848.0,
      "activeCases": 103325.0,
      "critical": 3987.0,
      "totalCases1M": 3585.0,
      "deaths1M": 391.0,
      "totalTests": 1056915.0,
      "tests1M": 8189.0
    },
    {
      "country": "Canada",
      "continent": "North America",
      "population": 3.7775022E7,
      "totalCases": 118561.0,
      "totalDeaths": 8966.0,
      "totalRecovered": 103106.0,
      "activeCases": 6489.0,
      "critical": 2263.0,
      "totalCases1M": 3139.0,
      "deaths1M": 237.0,
      "totalTests": 4319172.0,
      "tests1M": 114339.0
    },
    {
      "country": "Dominican Republic",
      "continent": "North America",
      "population": 1.0858648E7,
      "totalCases": 76536.0,
      "totalDeaths": 1246.0,
      "totalRecovered": 40539.0,
      "activeCases": 34751.0,
      "critical": 317.0,
      "totalCases1M": 7048.0,
      "deaths1M": 115.0,
      "totalTests": 281926.0,
      "tests1M": 25963.0
    },
    {
      "country": "Panama",
      "continent": "North America",
      "population": 4321282.0,
      "totalCases": 71418.0,
      "totalDeaths": 1574.0,
      "totalRecovered": 45658.0,
      "activeCases": 24186.0,
      "critical": 161.0,
      "totalCases1M": 16527.0,
      "deaths1M": 364.0,
      "totalTests": 240995.0,
      "tests1M": 55769.0
    },
    {
      "country": "Guatemala",
      "continent": "North America",
      "population": 1.7946899E7,
      "totalCases": 54339.0,
      "totalDeaths": 2119.0,
      "totalRecovered": 42070.0,
      "activeCases": 10150.0,
      "critical": 5.0,
      "totalCases1M": 3028.0,
      "deaths1M": 118.0,
      "totalTests": 172712.0,
      "tests1M": 9624.0
    },
    {
      "country": "Honduras",
      "continent": "North America",
      "population": 9919704.0,
      "totalCases": 45098.0,
      "totalDeaths": 1423.0,
      "totalRecovered": 6116.0,
      "activeCases": 37559.0,
      "critical": 52.0,
      "totalCases1M": 4546.0,
      "deaths1M": 143.0,
      "totalTests": 109292.0,
      "tests1M": 11018.0
    },
    {
      "country": "Costa Rica",
      "continent": "North America",
      "population": 5098730.0,
      "totalCases": 21070.0,
      "totalDeaths": 200.0,
      "totalRecovered": 7038.0,
      "activeCases": 13832.0,
      "critical": 103.0,
      "totalCases1M": 4132.0,
      "deaths1M": 39.0,
      "totalTests": 96110.0,
      "tests1M": 18850.0
    },
    {
      "country": "El Salvador",
      "continent": "North America",
      "population": 6489514.0,
      "totalCases": 19126.0,
      "totalDeaths": 513.0,
      "totalRecovered": 9236.0,
      "activeCases": 9377.0,
      "critical": 509.0,
      "totalCases1M": 2947.0,
      "deaths1M": 79.0,
      "totalTests": 251271.0,
      "tests1M": 38720.0
    },
    {
      "country": "Haiti",
      "continent": "North America",
      "population": 1.1416103E7,
      "totalCases": 7544.0,
      "totalDeaths": 171.0,
      "totalRecovered": 4832.0,
      "activeCases": 2541.0,
      "totalCases1M": 661.0,
      "deaths1M": 15.0,
      "totalTests": 18443.0,
      "tests1M": 1616.0
    },
    {
      "country": "Nicaragua",
      "continent": "North America",
      "population": 6632263.0,
      "totalCases": 3902.0,
      "totalDeaths": 123.0,
      "totalRecovered": 2913.0,
      "activeCases": 866.0,
      "totalCases1M": 588.0,
      "deaths1M": 19.0
    },
    {
      "country": "Cuba",
      "continent": "North America",
      "population": 1.1325899E7,
      "totalCases": 2775.0,
      "totalDeaths": 88.0,
      "totalRecovered": 2409.0,
      "activeCases": 278.0,
      "critical": 4.0,
      "totalCases1M": 245.0,
      "deaths1M": 8.0,
      "totalTests": 285471.0,
      "tests1M": 25205.0
    },
    {
      "country": "Jamaica",
      "continent": "North America",
      "population": 2962478.0,
      "totalCases": 958.0,
      "totalDeaths": 12.0,
      "totalRecovered": 745.0,
      "activeCases": 201.0,
      "totalCases1M": 323.0,
      "deaths1M": 4.0,
      "totalTests": 41840.0,
      "tests1M": 14123.0
    },
    {
      "country": "Bahamas",
      "continent": "North America",
      "population": 393616.0,
      "totalCases": 761.0,
      "totalDeaths": 14.0,
      "totalRecovered": 91.0,
      "activeCases": 656.0,
      "critical": 1.0,
      "totalCases1M": 1933.0,
      "deaths1M": 36.0,
      "totalTests": 4814.0,
      "tests1M": 12230.0
    },
    {
      "country": "Guadeloupe",
      "continent": "North America",
      "population": 400131.0,
      "totalCases": 279.0,
      "totalDeaths": 14.0,
      "totalRecovered": 179.0,
      "activeCases": 86.0,
      "totalCases1M": 697.0,
      "deaths1M": 35.0,
      "totalTests": 18476.0,
      "tests1M": 46175.0
    },
    {
      "country": "Martinique",
      "continent": "North America",
      "population": 375235.0,
      "totalCases": 276.0,
      "totalDeaths": 15.0,
      "totalRecovered": 98.0,
      "activeCases": 163.0,
      "critical": 1.0,
      "totalCases1M": 736.0,
      "deaths1M": 40.0,
      "totalTests": 12227.0,
      "tests1M": 32585.0
    },
    {
      "country": "Aruba",
      "continent": "North America",
      "population": 106812.0,
      "totalCases": 263.0,
      "totalDeaths": 3.0,
      "totalRecovered": 114.0,
      "activeCases": 146.0,
      "totalCases1M": 2462.0,
      "deaths1M": 28.0,
      "totalTests": 14047.0,
      "tests1M": 131511.0
    },
    {
      "country": "Trinidad and Tobago",
      "continent": "North America",
      "population": 1399950.0,
      "totalCases": 210.0,
      "totalDeaths": 8.0,
      "totalRecovered": 135.0,
      "activeCases": 67.0,
      "totalCases1M": 150.0,
      "deaths1M": 6.0,
      "totalTests": 9559.0,
      "tests1M": 6828.0
    },
    {
      "country": "Cayman Islands",
      "continent": "North America",
      "population": 65798.0,
      "totalCases": 203.0,
      "totalDeaths": 1.0,
      "totalRecovered": 202.0,
      "activeCases": 0.0,
      "totalCases1M": 3085.0,
      "deaths1M": 15.0,
      "totalTests": 31108.0,
      "tests1M": 472780.0
    },
    {
      "country": "Sint Maarten",
      "continent": "North America",
      "population": 42924.0,
      "totalCases": 160.0,
      "totalDeaths": 16.0,
      "totalRecovered": 64.0,
      "activeCases": 80.0,
      "critical": 3.0,
      "totalCases1M": 3728.0,
      "deaths1M": 373.0,
      "totalTests": 1115.0,
      "tests1M": 25976.0
    },
    {
      "country": "Bermuda",
      "continent": "North America",
      "population": 62254.0,
      "totalCases": 157.0,
      "totalDeaths": 9.0,
      "totalRecovered": 144.0,
      "activeCases": 4.0,
      "totalCases1M": 2522.0,
      "deaths1M": 145.0,
      "totalTests": 26352.0,
      "tests1M": 423298.0
    },
    {
      "country": "Barbados",
      "continent": "North America",
      "population": 287411.0,
      "totalCases": 133.0,
      "totalDeaths": 7.0,
      "totalRecovered": 100.0,
      "activeCases": 26.0,
      "totalCases1M": 463.0,
      "deaths1M": 24.0,
      "totalTests": 12233.0,
      "tests1M": 42563.0
    },
    {
      "country": "Turks and Caicos",
      "continent": "North America",
      "population": 38768.0,
      "totalCases": 129.0,
      "totalDeaths": 2.0,
      "totalRecovered": 39.0,
      "activeCases": 88.0,
      "critical": 3.0,
      "totalCases1M": 3327.0,
      "deaths1M": 52.0,
      "totalTests": 1252.0,
      "tests1M": 32295.0
    },
    {
      "country": "Antigua and Barbuda",
      "continent": "North America",
      "population": 98010.0,
      "totalCases": 92.0,
      "totalDeaths": 3.0,
      "totalRecovered": 76.0,
      "activeCases": 13.0,
      "critical": 1.0,
      "totalCases1M": 939.0,
      "deaths1M": 31.0,
      "totalTests": 1500.0,
      "tests1M": 15305.0
    },
    {
      "country": "Belize",
      "continent": "North America",
      "population": 398312.0,
      "totalCases": 86.0,
      "totalDeaths": 2.0,
      "totalRecovered": 31.0,
      "activeCases": 53.0,
      "critical": 2.0,
      "totalCases1M": 216.0,
      "deaths1M": 5.0,
      "totalTests": 3679.0,
      "tests1M": 9236.0
    },
    {
      "country": "St. Vincent Grenadines",
      "continent": "North America",
      "population": 110976.0,
      "totalCases": 56.0,
      "totalRecovered": 46.0,
      "activeCases": 10.0,
      "totalCases1M": 505.0,
      "totalTests": 2447.0,
      "tests1M": 22050.0
    },
    {
      "country": "Saint Martin",
      "continent": "North America",
      "population": 38729.0,
      "totalCases": 53.0,
      "totalDeaths": 3.0,
      "totalRecovered": 41.0,
      "activeCases": 9.0,
      "critical": 1.0,
      "totalCases1M": 1368.0,
      "deaths1M": 77.0,
      "totalTests": 1183.0,
      "tests1M": 30546.0
    },
    {
      "country": "Curaao",
      "continent": "North America",
      "population": 164161.0,
      "totalCases": 31.0,
      "totalDeaths": 1.0,
      "totalRecovered": 28.0,
      "activeCases": 2.0,
      "totalCases1M": 189.0,
      "deaths1M": 6.0,
      "totalTests": 1080.0,
      "tests1M": 6579.0
    },
    {
      "country": "Saint Lucia",
      "continent": "North America",
      "population": 183712.0,
      "totalCases": 25.0,
      "totalRecovered": 24.0,
      "activeCases": 1.0,
      "totalCases1M": 136.0,
      "totalTests": 3895.0,
      "tests1M": 21202.0
    },
    {
      "country": "Grenada",
      "continent": "North America",
      "population": 112576.0,
      "totalCases": 24.0,
      "totalRecovered": 23.0,
      "activeCases": 1.0,
      "totalCases1M": 213.0,
      "totalTests": 6252.0,
      "tests1M": 55536.0
    },
    {
      "country": "Dominica",
      "continent": "North America",
      "population": 72004.0,
      "totalCases": 18.0,
      "totalRecovered": 18.0,
      "activeCases": 0.0,
      "totalCases1M": 250.0,
      "totalTests": 1005.0,
      "tests1M": 13958.0
    },
    {
      "country": "Saint Kitts and Nevis",
      "continent": "North America",
      "population": 53237.0,
      "totalCases": 17.0,
      "totalRecovered": 16.0,
      "activeCases": 1.0,
      "totalCases1M": 319.0,
      "totalTests": 1146.0,
      "tests1M": 21526.0
    },
    {
      "country": "Greenland",
      "continent": "North America",
      "population": 56780.0,
      "totalCases": 14.0,
      "totalRecovered": 14.0,
      "activeCases": 0.0,
      "totalCases1M": 247.0,
      "totalTests": 5977.0,
      "tests1M": 105266.0
    },
    {
      "country": "Montserrat",
      "continent": "North America",
      "population": 4992.0,
      "totalCases": 13.0,
      "totalDeaths": 1.0,
      "totalRecovered": 10.0,
      "activeCases": 2.0,
      "totalCases1M": 2604.0,
      "deaths1M": 200.0,
      "totalTests": 61.0,
      "tests1M": 12220.0
    },
    {
      "country": "Caribbean Netherlands",
      "continent": "North America",
      "population": 26247.0,
      "totalCases": 13.0,
      "totalRecovered": 7.0,
      "activeCases": 6.0,
      "totalCases1M": 495.0,
      "totalTests": 424.0,
      "tests1M": 16154.0
    }
  ]
}